buildgen/__init__.py
buildgen/__main__.py
buildgen/cli/__init__.py
buildgen/cli/commands.py
buildgen/cli/main.py
buildgen/cli/parsers.py
buildgen/cmake/__init__.py
buildgen/cmake/builder.py
buildgen/cmake/cli.py
buildgen/cmake/functions.py
buildgen/cmake/generator.py
buildgen/cmake/project_generator.py
buildgen/cmake/variables.py
buildgen/common/__init__.py
buildgen/common/base.py
buildgen/common/platform.py
buildgen/common/project.py
buildgen/common/utils.py
buildgen/makefile/__init__.py
buildgen/makefile/builder.py
buildgen/makefile/cli.py
buildgen/makefile/functions.py
buildgen/makefile/generator.py
buildgen/makefile/variables.py
buildgen/recipes.py
buildgen/skbuild/__init__.py
buildgen/skbuild/generator.py
buildgen/skbuild/templates.py
buildgen/templates/__init__.py
buildgen/templates/c/app-with-lib/CMakeLists.txt.mako
buildgen/templates/c/app-with-lib/include/${name}/lib.h.mako
buildgen/templates/c/app-with-lib/src/lib.c.mako
buildgen/templates/c/app-with-lib/src/main.c.mako
buildgen/templates/c/executable/CMakeLists.txt.mako
buildgen/templates/c/executable/src/main.c.mako
buildgen/templates/c/full/CMakeLists.txt.mako
buildgen/templates/c/full/include/${name}/lib.h.mako
buildgen/templates/c/full/src/lib.c.mako
buildgen/templates/c/full/src/main.c.mako
buildgen/templates/c/full/tests/test_main.c.mako
buildgen/templates/c/header-only/CMakeLists.txt.mako
buildgen/templates/c/header-only/include/${name}/lib.h.mako
buildgen/templates/c/library-with-tests/CMakeLists.txt.mako
buildgen/templates/c/library-with-tests/include/${name}/lib.h.mako
buildgen/templates/c/library-with-tests/src/lib.c.mako
buildgen/templates/c/library-with-tests/tests/test_main.c.mako
buildgen/templates/c/shared/CMakeLists.txt.mako
buildgen/templates/c/shared/include/${name}/lib.h.mako
buildgen/templates/c/shared/src/lib.c.mako
buildgen/templates/c/static/CMakeLists.txt.mako
buildgen/templates/c/static/include/${name}/lib.h.mako
buildgen/templates/c/static/src/lib.c.mako
buildgen-0.1.9.dist-info/WHEEL
buildgen-0.1.9.dist-info/entry_points.txt
buildgen-0.1.9.dist-info/METADATA
buildgen-0.1.9.dist-info/RECORD
