Metadata-Version: 2.4
Name: buildgen
Version: 0.1.9
Summary: Build system generator - Makefile, CMake, scikit-build-core and more.
Keywords: makefile,cmake,build-system,code-generation,cpp,c++
Author: Shakeeb Alireza
Author-email: Shakeeb Alireza <shakfu@users.noreply.github.com>
License-Expression: GPL-3.0-or-later
Classifier: Development Status :: 3 - Alpha
Classifier: Environment :: Console
Classifier: Intended Audience :: Developers
Classifier: License :: OSI Approved :: GNU General Public License v3 or later (GPLv3+)
Classifier: Operating System :: OS Independent
Classifier: Programming Language :: Python :: 3
Classifier: Programming Language :: Python :: 3.11
Classifier: Programming Language :: Python :: 3.12
Classifier: Programming Language :: Python :: 3.13
Classifier: Programming Language :: Python :: 3.14
Classifier: Topic :: Software Development :: Build Tools
Classifier: Topic :: Software Development :: Code Generators
Classifier: Typing :: Typed
Requires-Dist: mako>=1.3.10
Requires-Dist: pyyaml>=6.0.3
Requires-Python: >=3.11
Project-URL: Homepage, https://github.com/shakfu/buildgen
Project-URL: Repository, https://github.com/shakfu/buildgen
Project-URL: Issues, https://github.com/shakfu/buildgen/issues
Project-URL: Changelog, https://github.com/shakfu/buildgen/blob/main/CHANGELOG.md
